Workbook

Sheet Expenses 
A1: expense_id | B1: expense_date | C1: amount | D1: category | E1: description | F1: payment_method | G1: necessary | H1: location | I1: Expense_Type | J1: High_Necessary | K1: Description_Length. | L1: First_Letter | M1: Last_Letter | N1: Expense_Label | O1: Expense_Month
A2: 2 | B2: 46266 | C2: 30 | D2: Transport | E2: Bus | F2: Cash | G2: Yes | H2: City | I2: =IF(G2="yes","necessary","unnecessary") -> necessary | J2: =IF(AND(C2>100,G2="yes"),"High necessary","Other") -> Other | K2: =LEN(Table1[[#This Row],[description]]) -> 3 | L2: =LEFT(E2,1) -> B | M2: =RIGHT(E2,1) -> s | N2: =_xlfn.CONCAT(Table1[[#This Row],[category]],"-",Table1[[#This Row],[description]]) -> Transport-Bus | O2: =CHOOSE(MONTH(B2),"January","February","March","April","May","June","July","August","September","October","November","December") -> September
A3: 10 | B3: 46270 | C3: 40 | D3: Transport | E3: Bus | F3: Cash | G3: Yes | H3: City | I3: =IF(G3="yes","necessary","unnecessary") -> necessary | J3: =IF(AND(C3>100,G3="yes"),"High necessary","Other") -> Other | K3: =LEN(Table1[[#This Row],[description]]) -> 3 | L3: =LEFT(E3,1) -> B | M3: =RIGHT(E3,1) -> s | N3: =_xlfn.CONCAT(Table1[[#This Row],[category]],"-",Table1[[#This Row],[description]]) -> Transport-Bus | O3: =CHOOSE(MONTH(B3),"January","February","March","April","May","June","July","August","September","October","November","December") -> September
A4: 5 | B4: 46267 | C4: 50 | D4: Transport | E4: Auto | F4: Cash | G4: Yes | H4: City | I4: =IF(G4="yes","necessary","unnecessary") -> necessary | J4: =IF(AND(C4>100,G4="yes"),"High necessary","Other") -> Other | K4: =LEN(Table1[[#This Row],[description]]) -> 4 | L4: =LEFT(E4,1) -> A | M4: =RIGHT(E4,1) -> o | N4: =_xlfn.CONCAT(Table1[[#This Row],[category]],"-",Table1[[#This Row],[description]]) -> Transport-Auto | O4: =CHOOSE(MONTH(B4),"January","February","March","April","May","June","July","August","September","October","November","December") -> September
A5: 1 | B5: 46266 | C5: 60 | D5: Food | E5: Breakfast | F5: Cash | G5: Yes | H5: Home | I5: =IF(G5="yes","necessary","unnecessary") -> necessary | J5: =IF(AND(C5>100,G5="yes"),"High necessary","Other") -> Other | K5: =LEN(Table1[[#This Row],[description]]) -> 9 | L5: =LEFT(E5,1) -> B | M5: =RIGHT(E5,1) -> t | N5: =_xlfn.CONCAT(Table1[[#This Row],[category]],"-",Table1[[#This Row],[description]]) -> Food-Breakfast | O5: =CHOOSE(MONTH(B5),"January","February","March","April","May","June","July","August","September","October","November","December") -> September
A6: 9 | B6: 46268 | C6: 80 | D6: Food | E6: Dinner | F6: Cash | G6: Yes | H6: Restaurant | I6: =IF(G6="yes","necessary","unnecessary") -> necessary | J6: =IF(AND(C6>100,G6="yes"),"High necessary","Other") -> Other | K6: =LEN(Table1[[#This Row],[description]]) -> 6 | L6: =LEFT(E6,1) -> D | M6: =RIGHT(E6,1) -> r | N6: =_xlfn.CONCAT(Table1[[#This Row],[category]],"-",Table1[[#This Row],[description]]) -> Food-Dinner | O6: =CHOOSE(MONTH(B6),"January","February","March","April","May","June","July","August","September","October","November","December") -> September
A7: 7 | B7: 46269 | C7: 100 | D7: Food | E7: Snacks | F7: UPI | G7: No | H7: College | I7: =IF(G7="yes","necessary","unnecessary") -> unnecessary | J7: =IF(AND(C7>100,G7="yes"),"High necessary","Other") -> Other | K7: =LEN(Table1[[#This Row],[description]]) -> 6 | L7: =LEFT(E7,1) -> S | M7: =RIGHT(E7,1) -> s | N7: =_xlfn.CONCAT(Table1[[#This Row],[category]],"-",Table1[[#This Row],[description]]) -> Food-Snacks | O7: =CHOOSE(MONTH(B7),"January","February","March","April","May","June","July","August","September","October","November","December") -> September
A8: 4 | B8: 46267 | C8: 120 | D8: Food | E8: Lunch | F8: UPI | G8: Yes | H8: College | I8: =IF(G8="yes","necessary","unnecessary") -> necessary | J8: =IF(AND(C8>100,G8="yes"),"High necessary","Other") -> High necessary | K8: =LEN(Table1[[#This Row],[description]]) -> 5 | L8: =LEFT(E8,1) -> L | M8: =RIGHT(E8,1) -> h | N8: =_xlfn.CONCAT(Table1[[#This Row],[category]],"-",Table1[[#This Row],[description]]) -> Food-Lunch | O8: =CHOOSE(MONTH(B8),"January","February","March","April","May","June","July","August","September","October","November","December") -> September
A9: 8 | B9: 46269 | C9: 200 | D9: Education | E9: Books | F9: UPI | G9: Yes | H9: Bookstore | I9: =IF(G9="yes","necessary","unnecessary") -> necessary | J9: =IF(AND(C9>100,G9="yes"),"High necessary","Other") -> High necessary | K9: =LEN(Table1[[#This Row],[description]]) -> 5 | L9: =LEFT(E9,1) -> B | M9: =RIGHT(E9,1) -> s | N9: =_xlfn.CONCAT(Table1[[#This Row],[category]],"-",Table1[[#This Row],[description]]) -> Education-Books | O9: =CHOOSE(MONTH(B9),"January","February","March","April","May","June","July","August","September","October","November","December") -> September
A10: 3 | B10: 46266 | C10: 250 | D10: Shopping | E10: T-shirt | F10: UPI | G10: No | H10: Mall | I10: =IF(G10="yes","necessary","unnecessary") -> unnecessary | J10: =IF(AND(C10>100,G10="yes"),"High necessary","Other") -> Other | K10: =LEN(Table1[[#This Row],[description]]) -> 7 | L10: =LEFT(E10,1) -> T | M10: =RIGHT(E10,1) -> t | N10: =_xlfn.CONCAT(Table1[[#This Row],[category]],"-",Table1[[#This Row],[description]]) -> Shopping-T-shirt | O10: =CHOOSE(MONTH(B10),"January","February","March","April","May","June","July","August","September","October","November","December") -> September
A11: 6 | B11: 46268 | C11: 500 | D11: Entertainment | E11: Movie | F11: UPI | G11: No | H11: Theatre | I11: =IF(G11="yes","necessary","unnecessary") -> unnecessary | J11: =IF(AND(C11>100,G11="yes"),"High necessary","Other") -> Other | K11: =LEN(Table1[[#This Row],[description]]) -> 5 | L11: =LEFT(E11,1) -> M | M11: =RIGHT(E11,1) -> e | N11: =_xlfn.CONCAT(Table1[[#This Row],[category]],"-",Table1[[#This Row],[description]]) -> Entertainment-Movie | O11: =CHOOSE(MONTH(B11),"January","February","March","April","May","June","July","August","September","October","November","December") -> September

Sheet Monthly_Budget
A1: budget_id | B1: month | C1: planned_amount | D1: category
A2: 1 | B2: 46266 | C2: 5000 | D2: Food
A3: 2 | B3: 46266 | C3: 2000 | D3: Transport
A4: 3 | B4: 46266 | C4: 3000 | D4: Education
A5: 4 | B5: 46266 | C5: 2000 | D5: Shopping
A6: 5 | B6: 46266 | C6: 1500 | D6: Entertainment

Sheet Analysis 
A1: Total spending | B1: 1430 | D1: Text | F1: category | G1: Budget | I1: Expense_id | J1: Category | K1: Amount | P1: Total spending | Q1: Transactions | R1: AverageExpense | S1: Highest Expense | T1: Lowest Expenses
A2: Total Transactions | B2: =COUNT('Expenses '!A2:A11) -> 10 | D2: 100 | F2: food | G2: 5000 | I2: 1 | J2: meals | K2: 60 | P2: 1430 | Q2: 10 | R2: 143 | S2: 500 | T2: 30
A3: Average Expenses | B3: =AVERAGE('Expenses '!C2:C11) -> 143 | D3: 200 | F3: transport | G3: 2000 | I3: 2 | J3: transport | K3: 30
D4: 300 | F4: education | G4: 3000 | I4: 3 | J4: meals | K4: 60 | P4: category | Q4: Total spending | S4: Category | T4: Budget | U4: Actual | V4: Remaining
B5: =SUM('Expenses '!C2:C11) -> 1430 | D5: =SUM(D2:D4) -> 600 | F5: shopping | G5: 2000 | I5: 3 | J5: meals | K5: 60 | P5: Food | Q5: =SUMIF(Table1[category],P5,Table1[amount]) -> 360 | S5: Food | T5: 5000 | U5: 360 | V5: 4640
B6: =AVERAGE('Expenses '!C2:C11) -> 143 | F6: entertainment | G6: 1500 | P6: Transport | Q6: =SUMIF(Table1[category],"Transport",Table1[amount]) -> 120 | S6: Transport | T6: 2000 | U6: 120 | V6: 1880
B7: =COUNT('Expenses '!C2:C11) -> 10 | D7: 10 | P7: Shopping | Q7: 250 | S7: Education | T7: 3000 | U7: 200 | V7: 2800
B8: =MIN('Expenses '!C2:C11) -> 30 | D8: 30 | F8: =VLOOKUP(F2,F2:G7,2,FALSE) -> 5000 | P8: Entertainment | Q8: 500 | S8: Shopping | T8: 2000 | U8: 250 | V8: 1750
B9: =MAX('Expenses '!C2:C11) -> 500 | D9: 30 | F9: =VLOOKUP(F4,F2:G6,2,FALSE) -> 3000 | P9: Education | Q9: 200 | S9: Entertainment | T9: 1500 | U9: 500 | V9: 1000
B10: =SUMIF('Expenses '!D2:D10,'Expenses '!D6,Table1[amount]) -> 360 | D10: =D7 -> 10 | F10: =VLOOKUP(F6,F2:G6,2,FALSE) -> 1500
B11: =COUNT('Expenses '!A5:A8,'Expenses '!D5:D8) -> 4 | D11: 30 | F11: =INDEX(G2:G6,MATCH(F6,F2:F6,0)) -> 1500 | M11: " Food "
B12: =COUNTIF(Table1[payment_method],'Expenses '!F8) -> 5 | D12: 100 | M12: =TRIM(M11) -> " Food "
B13: =SUMIFS(Table1[amount],Table1[category],'Expenses '!D7,Table1[necessary],'Expenses '!G4) -> 260 | D13: 100 | M13: Food-
B14: =COUNTIFS(Table1[category],'Expenses '!D5,Table1[necessary],'Expenses '!G4) -> 3 | D14: 100 | F14: =F6="Entertainment" -> TRUE | M14: =SUBSTITUTE(M13,"-","") -> Food
B15: =IFERROR(1000/0,"Invalid calculation") -> Invalid calculation | D15: =D13*3 -> 300 | F15: =MATCH("Entertainment",F2:F6,0) -> 5 | M15: =UPPER(M14) -> FOOD
B16: =ROUND(AVERAGE(Table1[amount]),2) -> 143 | D16: =$D$13*4 -> 400 | F16: =TRIM(F6) -> entertainment | M16: =LOWER(M14) -> food
B17: =MONTH('Expenses '!B2) -> 9 | D17: =$D$13*4 -> 400 | F17: =F6="Entertainment" -> TRUE | M17: =PROPER(M14) -> Food
B18: =DAY('Expenses '!B2) -> 1 | F18: =F6="Entertainment" -> TRUE | M18: 69
B19: =YEAR('Expenses '!B2) -> 2026 | M19: =VALUE(M18) -> 69
B20: =AVERAGEIF(Table1[category],"food",Table1[amount]) -> 90
B21: =AVERAGEIFS(Table1[amount],Table1[category],'Expenses '!D8,Table1[necessary],"yes") -> 86.666667 | M21: =MAX(Table1[amount]) -> 500
B22: =_xlfn.XLOOKUP("Education",Monthly_Budget!D2:D6,Monthly_Budget!C2:C6) -> 3000 | M22: =MIN(Table1[amount]) -> 30
B23: =_xlfn.XLOOKUP(Monthly_Budget!D5,Monthly_Budget!D2:D6,Monthly_Budget!C2:C6) -> 2000
B24: =_xlfn.XLOOKUP(Monthly_Budget!D3,Monthly_Budget!D2:D6,Monthly_Budget!C2:C6) -> 2000
P30: EXPENSE TYPE | Q30: TOTAL SPENDING
P31: Necessary | Q31: =60+30+120+50+80+200+40 -> 580
P32: Unnecessary | Q32: =250+500+100 -> 850
O53: Chart Date | P53: Daily Spending
O54: 46266 | P54: 340
O55: 46267 | P55: 170
O56: 46268 | P56: 580
O57: 46269 | P57: 300
O58: 46270 | P58: 40
